eipiphany_seda/__init__.py
eipiphany_seda/component/__init__.py
eipiphany_seda/component/seda_configuration.py
eipiphany_seda/component/seda_endpoint.py
eipiphany_seda/component/seda_source.py
eipiphany_seda-0.1.0.dev20230306154257.dist-info/METADATA
eipiphany_seda-0.1.0.dev20230306154257.dist-info/WHEEL
eipiphany_seda-0.1.0.dev20230306154257.dist-info/top_level.txt
eipiphany_seda-0.1.0.dev20230306154257.dist-info/RECORD
